ibm_aigov_facts_client/__init__.py
ibm_aigov_facts_client/version.py
ibm_aigov_facts_client/_wrappers/__init__.py
ibm_aigov_facts_client/_wrappers/requests.py
ibm_aigov_facts_client/base_classes/__init__.py
ibm_aigov_facts_client/base_classes/auth.py
ibm_aigov_facts_client/base_classes/common.py
ibm_aigov_facts_client/client/__init__.py
ibm_aigov_facts_client/client/_importhooks.py
ibm_aigov_facts_client/client/autolog.py
ibm_aigov_facts_client/client/fact_trace.py
ibm_aigov_facts_client/client/manual_log.py
ibm_aigov_facts_client/custom/__init__.py
ibm_aigov_facts_client/custom/custom_exp.py
ibm_aigov_facts_client/custom/custom_file_store.py
ibm_aigov_facts_client/export/__init__.py
ibm_aigov_facts_client/export/export_facts.py
ibm_aigov_facts_client/export/export_facts_manual.py
ibm_aigov_facts_client/factsheet/__init__.py
ibm_aigov_facts_client/factsheet/approaches.py
ibm_aigov_facts_client/factsheet/asset_utils_experiments.py
ibm_aigov_facts_client/factsheet/asset_utils_inventory.py
ibm_aigov_facts_client/factsheet/asset_utils_me.py
ibm_aigov_facts_client/factsheet/asset_utils_me_prompt.py
ibm_aigov_facts_client/factsheet/asset_utils_model.py
ibm_aigov_facts_client/factsheet/asset_utils_prompt.py
ibm_aigov_facts_client/factsheet/asset_utils_runs.py
ibm_aigov_facts_client/factsheet/assets.py
ibm_aigov_facts_client/factsheet/centralized_model.py
ibm_aigov_facts_client/factsheet/external_deployments.py
ibm_aigov_facts_client/factsheet/external_modelfacts_utility.py
ibm_aigov_facts_client/factsheet/factsheet_utility.py
ibm_aigov_facts_client/factsheet/html_parser.py
ibm_aigov_facts_client/factsheet/utils.py
ibm_aigov_facts_client/store/__init__.py
ibm_aigov_facts_client/store/abstract_payload_manual.py
ibm_aigov_facts_client/store/abstract_payload_store.py
ibm_aigov_facts_client/store/autolog/__init__.py
ibm_aigov_facts_client/store/autolog/autolog_utils.py
ibm_aigov_facts_client/store/autolog/bst_payload_store.py
ibm_aigov_facts_client-1.0.207.dist-info/licenses/LICENSE
ibm_aigov_facts_client-1.0.207.dist-info/METADATA
ibm_aigov_facts_client-1.0.207.dist-info/WHEEL
ibm_aigov_facts_client-1.0.207.dist-info/entry_points.txt
ibm_aigov_facts_client-1.0.207.dist-info/top_level.txt
ibm_aigov_facts_client-1.0.207.dist-info/RECORD
