Metadata-Version: 2.4
Name: ibm_aigov_facts_client
Version: 1.0.207
Summary: FactSheetService ML facts collection utility
Author: IBM
License: Apache 2.0
Requires-Python: >=3.7
License-File: LICENSE
Requires-Dist: pandas
Requires-Dist: numpy
Requires-Dist: mlflow-skinny==2.20.1
Requires-Dist: requests<3.0,>=2.0
Requires-Dist: ibm-cloud-sdk-core==3.24.2
Requires-Dist: sqlparse>=0.3.1
Requires-Dist: docutils<0.16,>=0.10
Requires-Dist: timeout_decorator
Requires-Dist: python-magic
Requires-Dist: pillow
Requires-Dist: boto3
Requires-Dist: ibm_watsonx_ai
Dynamic: author
Dynamic: description
Dynamic: description-content-type
Dynamic: license
Dynamic: license-file
Dynamic: requires-dist
Dynamic: requires-python
Dynamic: summary
